nonebot_plugin_whateat_pic-1.5.7.dist-info/METADATA
nonebot_plugin_whateat_pic-1.5.7.dist-info/WHEEL
nonebot_plugin_whateat_pic-1.5.7.dist-info/entry_points.txt
nonebot_plugin_whateat_pic-1.5.7.dist-info/licenses/LICENSE
nonebot_plugin_whateat_pic/__init__.py
nonebot_plugin_whateat_pic/check_on_statup.py
nonebot_plugin_whateat_pic/check_user_data.py
nonebot_plugin_whateat_pic/config.py
nonebot_plugin_whateat_pic/files.py
nonebot_plugin_whateat_pic/matcher.py
nonebot_plugin_whateat_pic/menu.py
nonebot_plugin_whateat_pic/menu_res/FZSJ-QINGCRJ.TTF
nonebot_plugin_whateat_pic/menu_res/menu_bg.jpg
nonebot_plugin_whateat_pic/random_pic.py
nonebot_plugin_whateat_pic-1.5.7.dist-info/RECORD
