Metadata-Version: 2.1
Name: nonebot-plugin-whateat-pic
Version: 1.5.7
Summary: 基于Nonebot2的今天吃什么（离线版）
Author: Cvandia
Author-Email: Cvandia <106718176+Cvandia@users.noreply.github.com>
License: MIT
Project-URL: homepage, https://github.com/Cvandia/nonebot-plugin-whateat-pic
Project-URL: repository, https://github.com/Cvandia/nonebot-plugin-whateat-pic
Requires-Python: <4,>=3.9
Requires-Dist: nonebot2>=2.0.0
Requires-Dist: httpx>=0.19.0
Requires-Dist: pillow>=10.4.0
Requires-Dist: nonebot-plugin-alconna<1.0.0,>=0.53.1
Requires-Dist: rich<14.0.0,>=13.9.4
Requires-Dist: nonebot-plugin-apscheduler>=0.5.0
Requires-Dist: nonebot-plugin-localstore>=0.7.4
